LICENSE
MANIFEST.in
README.rst
requirements.txt
setup.py
itauscraper/__init__.py
itauscraper/__main__.py
itauscraper/cli.py
itauscraper/converter.py
itauscraper/itertools.py
itauscraper/pages.py
itauscraper/scraper.py
itauscraper.egg-info/PKG-INFO
itauscraper.egg-info/SOURCES.txt
itauscraper.egg-info/dependency_links.txt
itauscraper.egg-info/entry_points.txt
itauscraper.egg-info/not-zip-safe
itauscraper.egg-info/requires.txt
itauscraper.egg-info/top_level.txt