Metadata-Version: 1.1
Name: itauscraper
Version: 1.0
Summary: Scraper para baixar seus extratos do Itaú com um comando.
Home-page: http://github.com/henriquebastos/itauscraper/
Author: Henrique Bastos
Author-email: henrique@bastos.net
License: GNU LGPLv3
Keywords: scraper,requests,lxml,itau,bank,finance,accounting
Platform: any
Classifier: Development Status :: 5 - Production/Stable
Classifier: Environment :: Console
Classifier: Intended Audience :: Financial and Insurance Industry
Classifier: License :: OSI Approved :: GNU Lesser General Public License v3 (LGPLv3)
Classifier: Natural Language :: Portuguese (Brazilian)
Classifier: Programming Language :: Python :: 3.4
Classifier: Programming Language :: Python :: 3.5
Classifier: Programming Language :: Python :: 3.6
Classifier: Programming Language :: Python :: 3 :: Only
Classifier: Topic :: Office/Business :: Financial :: Accounting
Classifier: Topic :: Utilities
